odoo/addons/pos_invoice_send_mail/README.rst
odoo/addons/pos_invoice_send_mail/__init__.py
odoo/addons/pos_invoice_send_mail/__manifest__.py
odoo/addons/pos_invoice_send_mail/i18n/es.po
odoo/addons/pos_invoice_send_mail/i18n/es_CL.po
odoo/addons/pos_invoice_send_mail/i18n/fr.po
odoo/addons/pos_invoice_send_mail/i18n/it.po
odoo/addons/pos_invoice_send_mail/i18n/pos_invoice_send_mail.pot
odoo/addons/pos_invoice_send_mail/models/__init__.py
odoo/addons/pos_invoice_send_mail/models/pos_config.py
odoo/addons/pos_invoice_send_mail/models/pos_order.py
odoo/addons/pos_invoice_send_mail/readme/CONFIGURE.rst
odoo/addons/pos_invoice_send_mail/readme/CONTRIBUTORS.rst
odoo/addons/pos_invoice_send_mail/readme/DESCRIPTION.rst
odoo/addons/pos_invoice_send_mail/readme/USAGE.rst
odoo/addons/pos_invoice_send_mail/static/description/icon.png
odoo/addons/pos_invoice_send_mail/static/description/index.html
odoo/addons/pos_invoice_send_mail/static/description/invoice-mail-config.png
odoo/addons/pos_invoice_send_mail/static/description/invoice-mail-screen.png
odoo/addons/pos_invoice_send_mail/static/src/js/models.js
odoo/addons/pos_invoice_send_mail/static/src/js/screens.js
odoo/addons/pos_invoice_send_mail/static/src/xml/pos.xml
odoo/addons/pos_invoice_send_mail/views/assets.xml
odoo/addons/pos_invoice_send_mail/views/pos_config.xml
odoo12_addon_pos_invoice_send_mail-12.0.1.0.0.99.dev16.dist-info/METADATA
odoo12_addon_pos_invoice_send_mail-12.0.1.0.0.99.dev16.dist-info/WHEEL
odoo12_addon_pos_invoice_send_mail-12.0.1.0.0.99.dev16.dist-info/top_level.txt
odoo12_addon_pos_invoice_send_mail-12.0.1.0.0.99.dev16.dist-info/RECORD
